{"compliance_information-privacy_index.md":"BXlHLaPw","overview-by-role_private-enterprise_index.md":"DzK0N5Df","overview-by-role_department_index.md":"DTKQfuAR","overview-by-field_index.md":"CReSmCQX","overview-by-field_statistics.md":"YYJibnIa","overview-by-role_clinic_index.md":"D5oN2ARW","products_scientific-suite_index.md":"CnAQj6tM","compliance_information-security_index.md":"BHEop2Iz","products_explore_index.md":"DowOxgb2","overview-by-field_engineering.md":"BkqqCjKm","use-cases_index.md":"D7Iwen_H","products_explore_test.md":"D-OzTwQV","tools_index.md":"DsVnWQ0A","tools_workbench_index.md":"Drva5Ijy","overview-by-role_scientist_index.md":"BkluPGIu","products_index.md":"YLP_ud4A","use-cases_image-processing.md":"D681ayi-","resources_index.md":"RhvLXopO","overview-by-role_teacher_index.md":"BOouChq5","overview-by-role_scientific-leader_index.md":"CPuOgV_V","resources_prices.md":"YPmhIDgu","overview-by-field_genomics.md":"DD1Jhk0q","overview-by-role_index.md":"C3xHXxla","resources_agreements.md":"DzE4yGXd","index.md":"D9aSTSyM","compliance_index.md":"OF3fkkuA","pillars_index.md":"CsdkV2DV","pillars_technology_index.md":"B6jP8MJQ","pillars_trust_index.md":"C2oaXSi0","compliance_quality-management_index.md":"DAUZdupo","use-cases_text-annotation.md":"DJ3IPVfd","use-cases_generative-ai.md":"D5BjCPsZ","use-cases_machine-learning.md":"B5pbxF3l","use-cases_phenotyping.md":"CLvoflZw","use-cases_sensitive-ai.md":"Ad8Jn231","products_evolve_index.md":"Vdp-pajb","pillars_collaboration_index.md":"QyoDrp89","use-cases_image-annotation.md":"Cj7S2-rT","team.md":"DIblVUn0"}
